generator/__init__.py
generator/human_dm.py
generator/gpt2/__init__.py
generator/gpt2/download_model.py
generator/gpt2/gpt2_generator.py
generator/gpt2/src/__init__.py
generator/gpt2/src/encoder.py
generator/gpt2/src/model.py
generator/gpt2/src/sample.py
generator/simple/__init__.py
generator/simple/finetune.py
other/__init__.py
other/cacher.py
story/__init__.py
story/story_manager.py
story/utils.py
aidungeon-1.0.0.dist-info/LICENSE
aidungeon-1.0.0.dist-info/METADATA
aidungeon-1.0.0.dist-info/WHEEL
aidungeon-1.0.0.dist-info/entry_points.txt
aidungeon-1.0.0.dist-info/top_level.txt
aidungeon-1.0.0.dist-info/RECORD
