Metadata-Version: 2.1
Name: aidungeon
Version: 1.0.0
Summary: AI Dungeon adventure!
Home-page: https://github.com/nickwalton/AIDungeon
License: MIT
Keywords: ai story dungeon game
Platform: UNKNOWN
Classifier: Programming Language :: Python :: 3.6
Classifier: Programming Language :: Python :: 3.7
Classifier: Programming Language :: Python :: 3.8
Classifier: Programming Language :: Python :: 3.9
